odoo/addons/l10n_it_delivery_note/README.rst
odoo/addons/l10n_it_delivery_note/__init__.py
odoo/addons/l10n_it_delivery_note/__manifest__.py
odoo/addons/l10n_it_delivery_note/hooks.py
odoo/addons/l10n_it_delivery_note/controllers/__init__.py
odoo/addons/l10n_it_delivery_note/controllers/portal.py
odoo/addons/l10n_it_delivery_note/data/delivery_note_data.xml
odoo/addons/l10n_it_delivery_note/demo/delivery_carrier_demo.xml
odoo/addons/l10n_it_delivery_note/demo/res_partner_demo.xml
odoo/addons/l10n_it_delivery_note/i18n/it.po
odoo/addons/l10n_it_delivery_note/i18n/l10n_it_delivery_note.pot
odoo/addons/l10n_it_delivery_note/mixins/__init__.py
odoo/addons/l10n_it_delivery_note/mixins/delivery_mixin.py
odoo/addons/l10n_it_delivery_note/mixins/picking_checker.py
odoo/addons/l10n_it_delivery_note/mixins/shipping_updater.py
odoo/addons/l10n_it_delivery_note/models/__init__.py
odoo/addons/l10n_it_delivery_note/models/account_invoice.py
odoo/addons/l10n_it_delivery_note/models/account_invoice_line.py
odoo/addons/l10n_it_delivery_note/models/res_company.py
odoo/addons/l10n_it_delivery_note/models/res_config_settings.py
odoo/addons/l10n_it_delivery_note/models/res_partner.py
odoo/addons/l10n_it_delivery_note/models/sale_order.py
odoo/addons/l10n_it_delivery_note/models/sale_order_line.py
odoo/addons/l10n_it_delivery_note/models/stock_delivery_note.py
odoo/addons/l10n_it_delivery_note/models/stock_delivery_note_line.py
odoo/addons/l10n_it_delivery_note/models/stock_delivery_note_type.py
odoo/addons/l10n_it_delivery_note/models/stock_location.py
odoo/addons/l10n_it_delivery_note/models/stock_picking.py
odoo/addons/l10n_it_delivery_note/models/stock_picking_goods_appearance.py
odoo/addons/l10n_it_delivery_note/models/stock_picking_transport_condition.py
odoo/addons/l10n_it_delivery_note/models/stock_picking_transport_method.py
odoo/addons/l10n_it_delivery_note/models/stock_picking_transport_reason.py
odoo/addons/l10n_it_delivery_note/readme/CONFIGURE.md
odoo_addon_l10n_it_delivery_note-18.0.1.0.4.1.dist-info/METADATA
odoo_addon_l10n_it_delivery_note-18.0.1.0.4.1.dist-info/WHEEL
odoo_addon_l10n_it_delivery_note-18.0.1.0.4.1.dist-info/top_level.txt
odoo_addon_l10n_it_delivery_note-18.0.1.0.4.1.dist-info/RECORD
