Metadata-Version: 2.1
Name: odoo-addon-l10n_it_delivery_note
Version: 18.0.1.0.4.1
Requires-Python: >=3.10
Requires-Dist: odoo-addon-delivery_carrier_partner==18.0.*
Requires-Dist: odoo==18.0.*
Summary: Crea, gestisce e fattura i DDT partendo dalle consegne
Home-page: https://github.com/OCA/l10n-italy
License: AGPL-3
Author: Marco Calcagni, Gianmarco Conte, Link IT Europe Srl, Odoo Community Association (OCA)
Author-email: support@odoo-community.org
Classifier: Programming Language :: Python
Classifier: Framework :: Odoo
Classifier: Framework :: Odoo :: 18.0
Classifier: License :: OSI Approved :: GNU Affero General Public License v3
